libcloud_api/__init__.py
libcloud_api/__main__.py
libcloud_api-0.3.0.dist-info/DESCRIPTION.rst
libcloud_api-0.3.0.dist-info/METADATA
libcloud_api-0.3.0.dist-info/metadata.json
libcloud_api-0.3.0.dist-info/RECORD
libcloud_api-0.3.0.dist-info/top_level.txt
libcloud_api-0.3.0.dist-info/WHEEL
