Metadata-Version: 2.0
Name: libcloud-api
Version: 0.3.0
Summary: Dynamic REST API for Apache Libcloud
Home-page: https://github.com/tonybaloney/libcloud.api
Author: Anthony Shaw
Author-email: anthonyshaw@apache.org
License: ISCL
Keywords: libcloud.api
Platform: UNKNOWN
Classifier: Development Status :: 2 - Pre-Alpha
Classifier: Intended Audience :: Developers
Classifier: License :: OSI Approved :: ISC License (ISCL)
Classifier: Natural Language :: English
Classifier: Programming Language :: Python :: 2
Classifier: Programming Language :: Python :: 2.6
Classifier: Programming Language :: Python :: 2.7
Classifier: Programming Language :: Python :: 3
Classifier: Programming Language :: Python :: 3.3
Classifier: Programming Language :: Python :: 3.4
Classifier: Programming Language :: Python :: 3.5
